<?xml version="1.0" encoding="utf-8" ?><dwsync><file name="COPYING.txt" server="ftp-cokes.heteml.net//web/" local="3805512081" remote="3617881200" Dst="-1" /><file name="Genericons.eot" server="ftp-cokes.heteml.net//web/" local="3805512081" remote="3617881200" Dst="-1" /><file name="Genericons.ttf" server="ftp-cokes.heteml.net//web/" local="3805512083" remote="3617881200" Dst="-1" /><file name="Genericons.svg" server="ftp-cokes.heteml.net//web/" local="3805512083" remote="3617881200" Dst="-1" /><file name="Genericons.woff" server="ftp-cokes.heteml.net//web/" local="3805512085" remote="3617881200" Dst="-1" /><file name="LICENSE.txt" server="ftp-cokes.heteml.net//web/" local="3805512085" remote="3617881200" Dst="-1" /><file name="README.md" server="ftp-cokes.heteml.net//web/" local="3805512087" remote="3617881200" Dst="-1" /><file name="example.html" server="ftp-cokes.heteml.net//web/" local="3805512087" remote="3617881200" Dst="-1" /><file name="genericons.css" server="ftp-cokes.heteml.net//web/" local="3805512089" remote="3617881200" Dst="-1" /><file name="COPYING.txt" server="ftp.lolipop.jp//web/" local="3805512081" remote="3805596600" Dst="-1" /><file name="Genericons.svg" server="ftp.lolipop.jp//web/" local="3805512083" remote="3805596600" Dst="-1" /><file name="genericons.css" server="ftp.lolipop.jp//web/" local="3805512089" remote="3805596600" Dst="-1" /><file name="README.md" server="ftp.lolipop.jp//web/" local="3805512087" remote="3805596600" Dst="-1" /><file name="example.html" server="ftp.lolipop.jp//web/" local="3805512087" remote="3805596600" Dst="-1" /><file name="Genericons.woff" server="ftp.lolipop.jp//web/" local="3805512085" remote="3805596600" Dst="-1" /><file name="Genericons.eot" server="ftp.lolipop.jp//web/" local="3805512081" remote="3805596600" Dst="-1" /><file name="LICENSE.txt" server="ftp.lolipop.jp//web/" local="3805512085" remote="3805596600" Dst="-1" /><file name="Genericons.ttf" server="ftp.lolipop.jp//web/" local="3805512083" remote="3805596600" Dst="-1" /></dwsync>