<?xml version="1.0" encoding="utf-8" ?><dwsync><file name="2k3-01-001n.html" server="ftp-cokes.heteml.net//web/" local="3805508705" remote="3667647600" Dst="-1" /><file name="2k3-01-001s.html" server="ftp-cokes.heteml.net//web/" local="3805508705" remote="3732534000" Dst="-1" /><file name="2k3-01-002m.html" server="ftp-cokes.heteml.net//web/" local="3805508705" remote="3667647600" Dst="-1" /><file name="2k3-01-002n.html" server="ftp-cokes.heteml.net//web/" local="3805508705" remote="3667647600" Dst="-1" /><file name="2k3-01-002s.html" server="ftp-cokes.heteml.net//web/" local="3805508706" remote="3732534000" Dst="-1" /><file name="2k3-01-003-s.html" server="ftp-cokes.heteml.net//web/" local="3805508706" remote="3732534000" Dst="-1" /><file name="2k3-01-003m.html" server="ftp-cokes.heteml.net//web/" local="3805508706" remote="3667647600" Dst="-1" /><file name="2k3-01-003n.html" server="ftp-cokes.heteml.net//web/" local="3805508706" remote="3667647600" Dst="-1" /><file name="2k3-01-003s.html" server="ftp-cokes.heteml.net//web/" local="3805508707" remote="3732534000" Dst="-1" /><file name="2k3-01-003t.html" server="ftp-cokes.heteml.net//web/" local="3805508707" remote="3732534000" Dst="-1" /><file name="2k3-01-004m.html" server="ftp-cokes.heteml.net//web/" local="3805508707" remote="3667647600" Dst="-1" /><file name="2k3-01-004n.html" server="ftp-cokes.heteml.net//web/" local="3805508707" remote="3667647600" Dst="-1" /><file name="2k3-01-004s.html" server="ftp-cokes.heteml.net//web/" local="3805508708" remote="3732534000" Dst="-1" /><file name="2k3-01-004t.html" server="ftp-cokes.heteml.net//web/" local="3805508708" remote="3732534000" Dst="-1" /><file name="2k3-01-005m.html" server="ftp-cokes.heteml.net//web/" local="3805508709" remote="3667647600" Dst="-1" /><file name="2k3-01-005n.html" server="ftp-cokes.heteml.net//web/" local="3805508709" remote="3667647600" Dst="-1" /><file name="2k3-01-005s.html" server="ftp-cokes.heteml.net//web/" local="3805508709" remote="3732534000" Dst="-1" /><file name="2k3-01-005t.html" server="ftp-cokes.heteml.net//web/" local="3805508709" remote="3732534000" Dst="-1" /><file name="2k3-01-006m.html" server="ftp-cokes.heteml.net//web/" local="3805508709" remote="3667647600" Dst="-1" /><file name="2k3-01-006n.html" server="ftp-cokes.heteml.net//web/" local="3805508710" remote="3667647600" Dst="-1" /><file name="2k3-01-006s.html" server="ftp-cokes.heteml.net//web/" local="3805508710" remote="3732534000" Dst="-1" /><file name="2k3-01-006t.html" server="ftp-cokes.heteml.net//web/" local="3805508711" remote="3732534000" Dst="-1" /><file name="2k3-01-007m.html" server="ftp-cokes.heteml.net//web/" local="3805508711" remote="3667647600" Dst="-1" /><file name="2k3-01-007n.html" server="ftp-cokes.heteml.net//web/" local="3805508711" remote="3732534000" Dst="-1" /><file name="2k3-01-007s.html" server="ftp-cokes.heteml.net//web/" local="3805508711" remote="3732534000" Dst="-1" /><file name="2k3-02-002m.html" server="ftp-cokes.heteml.net//web/" local="3805508712" remote="3667647600" Dst="-1" /><file name="2k3-02-002n.html" server="ftp-cokes.heteml.net//web/" local="3805508712" remote="3667647600" Dst="-1" /><file name="2k3-02-002t.html" server="ftp-cokes.heteml.net//web/" local="3805508712" remote="3732534000" Dst="-1" /><file name="2k3-02-003m.html" server="ftp-cokes.heteml.net//web/" local="3805508712" remote="3667647600" Dst="-1" /><file name="2k3-02-003n.html" server="ftp-cokes.heteml.net//web/" local="3805508713" remote="3667647600" Dst="-1" /><file name="2k3-02-003t.html" server="ftp-cokes.heteml.net//web/" local="3805508713" remote="3732534000" Dst="-1" /><file name="2k3-03-001s.html" server="ftp-cokes.heteml.net//web/" local="3805508713" remote="3732534000" Dst="-1" /><file name="2k3-03-002m.html" server="ftp-cokes.heteml.net//web/" local="3805508714" remote="3667647600" Dst="-1" /><file name="2k3-03-002n.html" server="ftp-cokes.heteml.net//web/" local="3805508714" remote="3667647600" Dst="-1" /><file name="2k3-03-002s.html" server="ftp-cokes.heteml.net//web/" local="3805508714" remote="3732534000" Dst="-1" /><file name="2k3-03-002t.html" server="ftp-cokes.heteml.net//web/" local="3805508714" remote="3732534000" Dst="-1" /><file name="2k3-03-003m.html" server="ftp-cokes.heteml.net//web/" local="3805508715" remote="3667647600" Dst="-1" /><file name="2k3-03-003n.html" server="ftp-cokes.heteml.net//web/" local="3805508715" remote="3667647600" Dst="-1" /><file name="2k3-03-003s.html" server="ftp-cokes.heteml.net//web/" local="3805508716" remote="3732534000" Dst="-1" /><file name="2k3-03-003t.html" server="ftp-cokes.heteml.net//web/" local="3805508716" remote="3732534000" Dst="-1" /><file name="2k3-03-08-001m.html" server="ftp-cokes.heteml.net//web/" local="3805508716" remote="3667647600" Dst="-1" /><file name="2k3-04-001m.html" server="ftp-cokes.heteml.net//web/" local="3805508716" remote="3667647600" Dst="-1" /><file name="2k3-04-001n.html" server="ftp-cokes.heteml.net//web/" local="3805508717" remote="3667647600" Dst="-1" /><file name="2k3-04-001t.html" server="ftp-cokes.heteml.net//web/" local="3805508717" remote="3732534000" Dst="-1" /><file name="2k3-04-002m.html" server="ftp-cokes.heteml.net//web/" local="3805508717" remote="3667647600" Dst="-1" /><file name="2k3-04-002n.html" server="ftp-cokes.heteml.net//web/" local="3805508718" remote="3667647600" Dst="-1" /><file name="2k3-04-002s.html" server="ftp-cokes.heteml.net//web/" local="3805508718" remote="3732534000" Dst="-1" /><file name="2k3-04-002t.html" server="ftp-cokes.heteml.net//web/" local="3805508718" remote="3732534000" Dst="-1" /><file name="2k3-04-003m.html" server="ftp-cokes.heteml.net//web/" local="3805508718" remote="3667647600" Dst="-1" /><file name="2k3-04-003n.html" server="ftp-cokes.heteml.net//web/" local="3805508719" remote="3667647600" Dst="-1" /><file name="2k3-04-003s.html" server="ftp-cokes.heteml.net//web/" local="3805508719" remote="3732534000" Dst="-1" /><file name="2k3-04-003t.html" server="ftp-cokes.heteml.net//web/" local="3805508719" remote="3732534000" Dst="-1" /><file name="2k3-04-004m.html" server="ftp-cokes.heteml.net//web/" local="3805508719" remote="3667647600" Dst="-1" /><file name="2k3-04-004t.html" server="ftp-cokes.heteml.net//web/" local="3805508720" remote="3732534000" Dst="-1" /><file name="2k3-04-005m.html" server="ftp-cokes.heteml.net//web/" local="3805508720" remote="3667647600" Dst="-1" /><file name="2k3-04-006t.html" server="ftp-cokes.heteml.net//web/" local="3805508720" remote="3732534000" Dst="-1" /><file name="2k3-04-007m.html" server="ftp-cokes.heteml.net//web/" local="3805508720" remote="3667647600" Dst="-1" /><file name="2k3-04-007t.html" server="ftp-cokes.heteml.net//web/" local="3805508721" remote="3732534000" Dst="-1" /><file name="2k3-05-001m.html" server="ftp-cokes.heteml.net//web/" local="3805508721" remote="3667647600" Dst="-1" /><file name="2k3-05-001n.html" server="ftp-cokes.heteml.net//web/" local="3805508722" remote="3667647600" Dst="-1" /><file name="2k3-05-001s.html" server="ftp-cokes.heteml.net//web/" local="3805508722" remote="3732534000" Dst="-1" /><file name="2k3-05-001t.html" server="ftp-cokes.heteml.net//web/" local="3805508722" remote="3732534000" Dst="-1" /><file name="2k3-05-002m.html" server="ftp-cokes.heteml.net//web/" local="3805508722" remote="3667647600" Dst="-1" /><file name="2k3-05-002n.html" server="ftp-cokes.heteml.net//web/" local="3805508722" remote="3667647600" Dst="-1" /><file name="2k3-05-002s.html" server="ftp-cokes.heteml.net//web/" local="3805508723" remote="3732534000" Dst="-1" /><file name="2k3-05-002t.html" server="ftp-cokes.heteml.net//web/" local="3805508723" remote="3732534000" Dst="-1" /><file name="2k3-05-003m.html" server="ftp-cokes.heteml.net//web/" local="3805508724" remote="3667647600" Dst="-1" /><file name="2k3-05-003n.html" server="ftp-cokes.heteml.net//web/" local="3805508724" remote="3667647600" Dst="-1" /><file name="2k3-05-003s.html" server="ftp-cokes.heteml.net//web/" local="3805508724" remote="3732534000" Dst="-1" /><file name="2k3-05-003t.html" server="ftp-cokes.heteml.net//web/" local="3805508724" remote="3732534000" Dst="-1" /><file name="2k3-05-004m.html" server="ftp-cokes.heteml.net//web/" local="3805508725" remote="3667647600" Dst="-1" /><file name="2k3-05-004n.html" server="ftp-cokes.heteml.net//web/" local="3805508725" remote="3667647600" Dst="-1" /><file name="2k3-05-004s.html" server="ftp-cokes.heteml.net//web/" local="3805508725" remote="3732534000" Dst="-1" /><file name="2k3-05-004t.html" server="ftp-cokes.heteml.net//web/" local="3805508725" remote="3732534000" Dst="-1" /><file name="2k3-05-005m.html" server="ftp-cokes.heteml.net//web/" local="3805508726" remote="3667647600" Dst="-1" /><file name="2k3-05-005s.html" server="ftp-cokes.heteml.net//web/" local="3805508726" remote="3732534000" Dst="-1" /><file name="2k3-05-005t.html" server="ftp-cokes.heteml.net//web/" local="3805508726" remote="3732534000" Dst="-1" /><file name="2k3-05-00m.html" server="ftp-cokes.heteml.net//web/" local="3805508727" remote="3667647600" Dst="-1" /><file name="2k3-06-001m.html" server="ftp-cokes.heteml.net//web/" local="3805508727" remote="3667647600" Dst="-1" /><file name="2k3-06-001n.html" server="ftp-cokes.heteml.net//web/" local="3805508727" remote="3667647600" Dst="-1" /><file name="2k3-06-001s.html" server="ftp-cokes.heteml.net//web/" local="3805508727" remote="3732534000" Dst="-1" /><file name="2k3-06-001t.html" server="ftp-cokes.heteml.net//web/" local="3805508728" remote="3732534000" Dst="-1" /><file name="2k3-06-002m.html" server="ftp-cokes.heteml.net//web/" local="3805508728" remote="3667647600" Dst="-1" /><file name="2k3-06-002n.html" server="ftp-cokes.heteml.net//web/" local="3805508729" remote="3667647600" Dst="-1" /><file name="2k3-06-002t.html" server="ftp-cokes.heteml.net//web/" local="3805508729" remote="3732534000" Dst="-1" /><file name="2k3-06-003m.html" server="ftp-cokes.heteml.net//web/" local="3805508729" remote="3667647600" Dst="-1" /><file name="2k3-06-003n.html" server="ftp-cokes.heteml.net//web/" local="3805508729" remote="3667647600" Dst="-1" /><file name="2k3-06-004m.html" server="ftp-cokes.heteml.net//web/" local="3805508730" remote="3667647600" Dst="-1" /><file name="2k3-06-005m.html" server="ftp-cokes.heteml.net//web/" local="3805508730" remote="3667647600" Dst="-1" /><file name="2k3-06-006m.html" server="ftp-cokes.heteml.net//web/" local="3805508730" remote="3667647600" Dst="-1" /><file name="2k3-07-001m.html" server="ftp-cokes.heteml.net//web/" local="3805508731" remote="3667647600" Dst="-1" /><file name="2k3-07-001n.html" server="ftp-cokes.heteml.net//web/" local="3805508731" remote="3667647600" Dst="-1" /><file name="2k3-07-001s.html" server="ftp-cokes.heteml.net//web/" local="3805508731" remote="3732534000" Dst="-1" /><file name="2k3-07-001t.html" server="ftp-cokes.heteml.net//web/" local="3805508731" remote="3732534000" Dst="-1" /><file name="2k3-07-002n.html" server="ftp-cokes.heteml.net//web/" local="3805508732" remote="3667647600" Dst="-1" /><file name="2k3-07-003m.html" server="ftp-cokes.heteml.net//web/" local="3805508732" remote="3667647600" Dst="-1" /><file name="2k3-07-003n.html" server="ftp-cokes.heteml.net//web/" local="3805508733" remote="3667647600" Dst="-1" /><file name="2k3-07-003s.html" server="ftp-cokes.heteml.net//web/" local="3805508733" remote="3732534000" Dst="-1" /><file name="2k3-07-003t.html" server="ftp-cokes.heteml.net//web/" local="3805508733" remote="3732534000" Dst="-1" /><file name="2k3-07-004m.html" server="ftp-cokes.heteml.net//web/" local="3805508733" remote="3667647600" Dst="-1" /><file name="2k3-07-004n.html" server="ftp-cokes.heteml.net//web/" local="3805508734" remote="3667647600" Dst="-1" /><file name="2k3-07-004t.html" server="ftp-cokes.heteml.net//web/" local="3805508734" remote="3732534000" Dst="-1" /><file name="2k3-08-001m.html" server="ftp-cokes.heteml.net//web/" local="3805508734" remote="3667647600" Dst="-1" /><file name="2k3-08-001n.html" server="ftp-cokes.heteml.net//web/" local="3805508734" remote="3667647600" Dst="-1" /><file name="2k3-08-001t.html" server="ftp-cokes.heteml.net//web/" local="3805508735" remote="3732534000" Dst="-1" /><file name="2k3-08-0021t.html" server="ftp-cokes.heteml.net//web/" local="3805508735" remote="3732534000" Dst="-1" /><file name="2k3-08-002m.html" server="ftp-cokes.heteml.net//web/" local="3805508735" remote="3667647600" Dst="-1" /><file name="2k3-08-002n.html" server="ftp-cokes.heteml.net//web/" local="3805508736" remote="3667647600" Dst="-1" /><file name="2k3-08-002t.html" server="ftp-cokes.heteml.net//web/" local="3805508736" remote="3732534000" Dst="-1" /><file name="2k3-08-003n.html" server="ftp-cokes.heteml.net//web/" local="3805508737" remote="3667647600" Dst="-1" /><file name="2k3-08-003m.html" server="ftp-cokes.heteml.net//web/" local="3805508737" remote="3667647600" Dst="-1" /><file name="2k3-08-004n.html" server="ftp-cokes.heteml.net//web/" local="3805508737" remote="3667647600" Dst="-1" /><file name="2k3-09-001m.html" server="ftp-cokes.heteml.net//web/" local="3805508737" remote="3667647600" Dst="-1" /><file name="2k3-09-001n.html" server="ftp-cokes.heteml.net//web/" local="3805508737" remote="3667647600" Dst="-1" /><file name="2k3-09-001s.html" server="ftp-cokes.heteml.net//web/" local="3805508737" remote="3732534000" Dst="-1" /><file name="2k3-09-001t.html" server="ftp-cokes.heteml.net//web/" local="3805508738" remote="3732534000" Dst="-1" /><file name="2k3-09-002n.html" server="ftp-cokes.heteml.net//web/" local="3805508738" remote="3667647600" Dst="-1" /><file name="2k3-09-002s.html" server="ftp-cokes.heteml.net//web/" local="3805508739" remote="3732534000" Dst="-1" /><file name="2k3-09-002t.html" server="ftp-cokes.heteml.net//web/" local="3805508739" remote="3732534000" Dst="-1" /><file name="2k3-09-003m.html" server="ftp-cokes.heteml.net//web/" local="3805508739" remote="3667647600" Dst="-1" /><file name="2k3-09-003n.html" server="ftp-cokes.heteml.net//web/" local="3805508740" remote="3667647600" Dst="-1" /><file name="2k3-09-003s.html" server="ftp-cokes.heteml.net//web/" local="3805508740" remote="3732534000" Dst="-1" /><file name="2k3-09-003t.html" server="ftp-cokes.heteml.net//web/" local="3805508740" remote="3732534000" Dst="-1" /><file name="2k3-09-004m.html" server="ftp-cokes.heteml.net//web/" local="3805508740" remote="3667647600" Dst="-1" /><file name="2k3-09-004n.html" server="ftp-cokes.heteml.net//web/" local="3805508741" remote="3667647600" Dst="-1" /><file name="2k3-09-004s.html" server="ftp-cokes.heteml.net//web/" local="3805508741" remote="3732534000" Dst="-1" /><file name="2k3-09-004t.html" server="ftp-cokes.heteml.net//web/" local="3805508741" remote="3732534000" Dst="-1" /><file name="2k3-09-005n.html" server="ftp-cokes.heteml.net//web/" local="3805508741" remote="3667647600" Dst="-1" /><file name="2k3-09-005s.html" server="ftp-cokes.heteml.net//web/" local="3805508742" remote="3732534000" Dst="-1" /><file name="2k3-10-001m.html" server="ftp-cokes.heteml.net//web/" local="3805508742" remote="3667647600" Dst="-1" /><file name="2k3-10-001n.html" server="ftp-cokes.heteml.net//web/" local="3805508742" remote="3667647600" Dst="-1" /><file name="2k3-10-002s.html" server="ftp-cokes.heteml.net//web/" local="3805508742" remote="3732534000" Dst="-1" /><file name="2k3-10-002t.html" server="ftp-cokes.heteml.net//web/" local="3805508743" remote="3732534000" Dst="-1" /><file name="2k3-10-003m.html" server="ftp-cokes.heteml.net//web/" local="3805508743" remote="3667647600" Dst="-1" /><file name="2k3-10-003n.html" server="ftp-cokes.heteml.net//web/" local="3805508744" remote="3667647600" Dst="-1" /><file name="2k3-10-003s.html" server="ftp-cokes.heteml.net//web/" local="3805508744" remote="3732534000" Dst="-1" /><file name="2k3-10-003t.html" server="ftp-cokes.heteml.net//web/" local="3805508744" remote="3732534000" Dst="-1" /><file name="2k3-10-004m.html" server="ftp-cokes.heteml.net//web/" local="3805508745" remote="3667647600" Dst="-1" /><file name="2k3-10-004n.html" server="ftp-cokes.heteml.net//web/" local="3805508745" remote="3667647600" Dst="-1" /><file name="2k3-10-005m.html" server="ftp-cokes.heteml.net//web/" local="3805508745" remote="3667647600" Dst="-1" /><file name="2k3-10-005n.html" server="ftp-cokes.heteml.net//web/" local="3805508745" remote="3667647600" Dst="-1" /><file name="2k3-10-005t.html" server="ftp-cokes.heteml.net//web/" local="3805508746" remote="3732534000" Dst="-1" /><file name="2k3-10-006m.html" server="ftp-cokes.heteml.net//web/" local="3805508746" remote="3667647600" Dst="-1" /><file name="2k3-10-006n.html" server="ftp-cokes.heteml.net//web/" local="3805508747" remote="3667647600" Dst="-1" /><file name="2k3-10-006t.html" server="ftp-cokes.heteml.net//web/" local="3805508747" remote="3732534000" Dst="-1" /><file name="2k3-10-007n.html" server="ftp-cokes.heteml.net//web/" local="3805508747" remote="3667647600" Dst="-1" /><file name="2k3-10-007t.html" server="ftp-cokes.heteml.net//web/" local="3805508747" remote="3732534000" Dst="-1" /><file name="2k3-10-008m.html" server="ftp-cokes.heteml.net//web/" local="3805508748" remote="3667647600" Dst="-1" /><file name="2k3-10-008n.html" server="ftp-cokes.heteml.net//web/" local="3805508748" remote="3667647600" Dst="-1" /><file name="2k3-10-009n.html" server="ftp-cokes.heteml.net//web/" local="3805508748" remote="3667647600" Dst="-1" /><file name="2k3-11-001m.html" server="ftp-cokes.heteml.net//web/" local="3805508749" remote="3667647600" Dst="-1" /><file name="2k3-11-001n.html" server="ftp-cokes.heteml.net//web/" local="3805508749" remote="3667647600" Dst="-1" /><file name="2k3-11-002m.html" server="ftp-cokes.heteml.net//web/" local="3805508749" remote="3667647600" Dst="-1" /><file name="2k3-11-002n.html" server="ftp-cokes.heteml.net//web/" local="3805508749" remote="3667647600" Dst="-1" /><file name="2k3-11-002s.html" server="ftp-cokes.heteml.net//web/" local="3805508750" remote="3732534000" Dst="-1" /><file name="2k3-11-003m.html" server="ftp-cokes.heteml.net//web/" local="3805508750" remote="3667647600" Dst="-1" /><file name="2k3-11-003s.html" server="ftp-cokes.heteml.net//web/" local="3805508750" remote="3732534000" Dst="-1" /><file name="2k3-11-003t.html" server="ftp-cokes.heteml.net//web/" local="3805508750" remote="3732534000" Dst="-1" /><file name="2k3-11-004m.html" server="ftp-cokes.heteml.net//web/" local="3805508751" remote="3667647600" Dst="-1" /><file name="2k3-11-004n.html" server="ftp-cokes.heteml.net//web/" local="3805508751" remote="3667647600" Dst="-1" /><file name="2k3-11-004s.html" server="ftp-cokes.heteml.net//web/" local="3805508752" remote="3732534000" Dst="-1" /><file name="2k3-11-005m.html" server="ftp-cokes.heteml.net//web/" local="3805508752" remote="3667647600" Dst="-1" /><file name="2k3-11-005n.html" server="ftp-cokes.heteml.net//web/" local="3805508752" remote="3667647600" Dst="-1" /><file name="2k3-11-005s.html" server="ftp-cokes.heteml.net//web/" local="3805508752" remote="3732534000" Dst="-1" /><file name="2k3-11-005t.html" server="ftp-cokes.heteml.net//web/" local="3805508753" remote="3732534000" Dst="-1" /><file name="2k3-11-006m.html" server="ftp-cokes.heteml.net//web/" local="3805508753" remote="3667647600" Dst="-1" /><file name="2k3-11-006n.html" server="ftp-cokes.heteml.net//web/" local="3805508753" remote="3667647600" Dst="-1" /><file name="2k3-11-006s.html" server="ftp-cokes.heteml.net//web/" local="3805508754" remote="3732534000" Dst="-1" /><file name="2k3-11-006t.html" server="ftp-cokes.heteml.net//web/" local="3805508754" remote="3732534000" Dst="-1" /><file name="2k3-11-007m.html" server="ftp-cokes.heteml.net//web/" local="3805508754" remote="3667647600" Dst="-1" /><file name="2k3-11-007n.html" server="ftp-cokes.heteml.net//web/" local="3805508754" remote="3667647600" Dst="-1" /><file name="2k3-12-001m.html" server="ftp-cokes.heteml.net//web/" local="3805508755" remote="3732534000" Dst="-1" /><file name="2k3-12-001n.html" server="ftp-cokes.heteml.net//web/" local="3805508755" remote="3667647600" Dst="-1" /><file name="2k3-12-002m.html" server="ftp-cokes.heteml.net//web/" local="3805508756" remote="3732534000" Dst="-1" /><file name="2k3-12-003n.html" server="ftp-cokes.heteml.net//web/" local="3805508756" remote="3667647600" Dst="-1" /><file name="2k3-12-003t.html" server="ftp-cokes.heteml.net//web/" local="3805508756" remote="3732534000" Dst="-1" /><file name="2k3-12-004m.html" server="ftp-cokes.heteml.net//web/" local="3805508756" remote="3732534000" Dst="-1" /><file name="2k3-12-004n.html" server="ftp-cokes.heteml.net//web/" local="3805508757" remote="3667647600" Dst="-1" /><file name="2k3-12-004t.html" server="ftp-cokes.heteml.net//web/" local="3805508757" remote="3732534000" Dst="-1" /><file name="2k3-12-005m.html" server="ftp-cokes.heteml.net//web/" local="3805508758" remote="3732534000" Dst="-1" /><file name="2k3-12-005n.html" server="ftp-cokes.heteml.net//web/" local="3805508758" remote="3667647600" Dst="-1" /><file name="2k3-12-005t.html" server="ftp-cokes.heteml.net//web/" local="3805508758" remote="3732534000" Dst="-1" /><file name="2k3-12-006n.html" server="ftp-cokes.heteml.net//web/" local="3805508758" remote="3667647600" Dst="-1" /><file name="2k3-12-007n.html" server="ftp-cokes.heteml.net//web/" local="3805508759" remote="3667647600" Dst="-1" /><file name="2k3-12-007t.html" server="ftp-cokes.heteml.net//web/" local="3805508759" remote="3732534000" Dst="-1" /><file name="2k3-12-008m.html" server="ftp-cokes.heteml.net//web/" local="3805508759" remote="3732534000" Dst="-1" /><file name="2k3-12-008n.html" server="ftp-cokes.heteml.net//web/" local="3805508760" remote="3667647600" Dst="-1" /><file name="2k3-12-008t.html" server="ftp-cokes.heteml.net//web/" local="3805508760" remote="3732534000" Dst="-1" /><file name="2k3-12-009m.html" server="ftp-cokes.heteml.net//web/" local="3805508760" remote="3732534000" Dst="-1" /><file name="2k3-12-009n.html" server="ftp-cokes.heteml.net//web/" local="3805508760" remote="3667647600" Dst="-1" /><file name="2k3-03-003n.html" server="ftp.lolipop.jp//web/" local="3805508715" remote="3805593840" Dst="-1" /><file name="2k3-10-006n.html" server="ftp.lolipop.jp//web/" local="3805508747" remote="3805593840" Dst="-1" /><file name="2k3-11-005n.html" server="ftp.lolipop.jp//web/" local="3805508752" remote="3805593840" Dst="-1" /><file name="2k3-01-003s.html" server="ftp.lolipop.jp//web/" local="3805508707" remote="3805593840" Dst="-1" /><file name="2k3-06-001m.html" server="ftp.lolipop.jp//web/" local="3805508727" remote="3805593840" Dst="-1" /><file name="2k3-01-006t.html" server="ftp.lolipop.jp//web/" local="3805508711" remote="3805593840" Dst="-1" /><file name="2k3-01-004m.html" server="ftp.lolipop.jp//web/" local="3805508707" remote="3805593840" Dst="-1" /><file name="2k3-09-004n.html" server="ftp.lolipop.jp//web/" local="3805508741" remote="3805593840" Dst="-1" /><file name="2k3-12-001m.html" server="ftp.lolipop.jp//web/" local="3805508755" remote="3805593840" Dst="-1" /><file name="2k3-12-003t.html" server="ftp.lolipop.jp//web/" local="3805508756" remote="3805593900" Dst="-1" /><file name="2k3-02-002n.html" server="ftp.lolipop.jp//web/" local="3805508712" remote="3805593900" Dst="-1" /><file name="2k3-06-001t.html" server="ftp.lolipop.jp//web/" local="3805508728" remote="3805593900" Dst="-1" /><file name="2k3-06-003m.html" server="ftp.lolipop.jp//web/" local="3805508729" remote="3805593900" Dst="-1" /><file name="2k3-01-001s.html" server="ftp.lolipop.jp//web/" local="3805508705" remote="3805593900" Dst="-1" /><file name="2k3-11-007n.html" server="ftp.lolipop.jp//web/" local="3805508754" remote="3805593900" Dst="-1" /><file name="2k3-10-008m.html" server="ftp.lolipop.jp//web/" local="3805508748" remote="3805593900" Dst="-1" /><file name="2k3-01-004t.html" server="ftp.lolipop.jp//web/" local="3805508708" remote="3805593900" Dst="-1" /><file name="2k3-01-006m.html" server="ftp.lolipop.jp//web/" local="3805508709" remote="3805593900" Dst="-1" /><file name="2k3-10-004n.html" server="ftp.lolipop.jp//web/" local="3805508745" remote="3805593900" Dst="-1" /><file name="2k3-07-004m.html" server="ftp.lolipop.jp//web/" local="3805508733" remote="3805593900" Dst="-1" /><file name="2k3-07-003s.html" server="ftp.lolipop.jp//web/" local="3805508733" remote="3805593900" Dst="-1" /><file name="2k3-08-001n.html" server="ftp.lolipop.jp//web/" local="3805508734" remote="3805593900" Dst="-1" /><file name="2k3-12-005t.html" server="ftp.lolipop.jp//web/" local="3805508758" remote="3805593900" Dst="-1" /><file name="2k3-05-003n.html" server="ftp.lolipop.jp//web/" local="3805508724" remote="3805593900" Dst="-1" /><file name="2k3-09-002n.html" server="ftp.lolipop.jp//web/" local="3805508738" remote="3805593900" Dst="-1" /><file name="2k3-01-002m.html" server="ftp.lolipop.jp//web/" local="3805508705" remote="3805593900" Dst="-1" /><file name="2k3-01-005s.html" server="ftp.lolipop.jp//web/" local="3805508709" remote="3805593900" Dst="-1" /><file name="2k3-06-005m.html" server="ftp.lolipop.jp//web/" local="3805508730" remote="3805593900" Dst="-1" /><file name="2k3-11-001n.html" server="ftp.lolipop.jp//web/" local="3805508749" remote="3805593900" Dst="-1" /><file name="2k3-01-007s.html" server="ftp.lolipop.jp//web/" local="3805508711" remote="3805593900" Dst="-1" /><file name="2k3-05-001n.html" server="ftp.lolipop.jp//web/" local="3805508722" remote="3805593900" Dst="-1" /><file name="2k3-12-005m.html" server="ftp.lolipop.jp//web/" local="3805508758" remote="3805593900" Dst="-1" /><file name="2k3-12-007t.html" server="ftp.lolipop.jp//web/" local="3805508759" remote="3805593900" Dst="-1" /><file name="2k3-08-003n.html" server="ftp.lolipop.jp//web/" local="3805508737" remote="3805593900" Dst="-1" /><file name="2k3-12-009n.html" server="ftp.lolipop.jp//web/" local="3805508760" remote="3805593900" Dst="-1" /><file name="2k3-04-002n.html" server="ftp.lolipop.jp//web/" local="3805508718" remote="3805593900" Dst="-1" /><file name="2k3-07-004t.html" server="ftp.lolipop.jp//web/" local="3805508734" remote="3805593900" Dst="-1" /><file name="2k3-07-001s.html" server="ftp.lolipop.jp//web/" local="3805508731" remote="3805593900" Dst="-1" /><file name="2k3-01-005t.html" server="ftp.lolipop.jp//web/" local="3805508709" remote="3805593900" Dst="-1" /><file name="2k3-08-0021t.html" server="ftp.lolipop.jp//web/" local="3805508735" remote="3805593900" Dst="-1" /><file name="2k3-01-007m.html" server="ftp.lolipop.jp//web/" local="3805508711" remote="3805593900" Dst="-1" /><file name="2k3-01-003-s.html" server="ftp.lolipop.jp//web/" local="3805508706" remote="3805593900" Dst="-1" /><file name="2k3-06-002m.html" server="ftp.lolipop.jp//web/" local="3805508728" remote="3805593900" Dst="-1" /><file name="2k3-11-006n.html" server="ftp.lolipop.jp//web/" local="3805508753" remote="3805593900" Dst="-1" /><file name="2k3-12-002m.html" server="ftp.lolipop.jp//web/" local="3805508756" remote="3805593900" Dst="-1" /><file name="2k3-02-003n.html" server="ftp.lolipop.jp//web/" local="3805508713" remote="3805593900" Dst="-1" /><file name="2k3-08-004n.html" server="ftp.lolipop.jp//web/" local="3805508737" remote="3805593900" Dst="-1" /><file name="2k3-10-005n.html" server="ftp.lolipop.jp//web/" local="3805508745" remote="3805593900" Dst="-1" /><file name="2k3-07-003t.html" server="ftp.lolipop.jp//web/" local="3805508733" remote="3805593900" Dst="-1" /><file name="2k3-07-001m.html" server="ftp.lolipop.jp//web/" local="3805508731" remote="3805593900" Dst="-1" /><file name="2k3-07-001t.html" server="ftp.lolipop.jp//web/" local="3805508731" remote="3805593900" Dst="-1" /><file name="2k3-07-003m.html" server="ftp.lolipop.jp//web/" local="3805508732" remote="3805593900" Dst="-1" /><file name="2k3-03-002n.html" server="ftp.lolipop.jp//web/" local="3805508714" remote="3805593900" Dst="-1" /><file name="2k3-10-007n.html" server="ftp.lolipop.jp//web/" local="3805508747" remote="3805593900" Dst="-1" /><file name="2k3-05-004n.html" server="ftp.lolipop.jp//web/" local="3805508725" remote="3805593900" Dst="-1" /><file name="2k3-09-005n.html" server="ftp.lolipop.jp//web/" local="3805508741" remote="3805593900" Dst="-1" /><file name="2k3-11-004n.html" server="ftp.lolipop.jp//web/" local="3805508751" remote="3805593900" Dst="-1" /><file name="2k3-01-002s.html" server="ftp.lolipop.jp//web/" local="3805508706" remote="3805593900" Dst="-1" /><file name="2k3-06-002t.html" server="ftp.lolipop.jp//web/" local="3805508729" remote="3805593900" Dst="-1" /><file name="2k3-12-004m.html" server="ftp.lolipop.jp//web/" local="3805508756" remote="3805593900" Dst="-1" /><file name="2k3-09-001n.html" server="ftp.lolipop.jp//web/" local="3805508737" remote="3805593900" Dst="-1" /><file name="2k3-06-004m.html" server="ftp.lolipop.jp//web/" local="3805508730" remote="3805593900" Dst="-1" /><file name="2k3-01-005m.html" server="ftp.lolipop.jp//web/" local="3805508709" remote="3805593900" Dst="-1" /><file name="2k3-01-006s.html" server="ftp.lolipop.jp//web/" local="3805508710" remote="3805593900" Dst="-1" /><file name="2k3-01-003t.html" server="ftp.lolipop.jp//web/" local="3805508707" remote="3805593900" Dst="-1" /><file name="2k3-10-003n.html" server="ftp.lolipop.jp//web/" local="3805508744" remote="3805593900" Dst="-1" /><file name="2k3-04-003n.html" server="ftp.lolipop.jp//web/" local="3805508719" remote="3805593900" Dst="-1" /><file name="2k3-08-002n.html" server="ftp.lolipop.jp//web/" local="3805508736" remote="3805593900" Dst="-1" /><file name="2k3-12-008n.html" server="ftp.lolipop.jp//web/" local="3805508760" remote="3805593900" Dst="-1" /><file name="2k3-04-001n.html" server="ftp.lolipop.jp//web/" local="3805508717" remote="3805593900" Dst="-1" /><file name="2k3-10-001n.html" server="ftp.lolipop.jp//web/" local="3805508742" remote="3805593900" Dst="-1" /><file name="2k3-01-004s.html" server="ftp.lolipop.jp//web/" local="3805508708" remote="3805593900" Dst="-1" /><file name="2k3-11-002n.html" server="ftp.lolipop.jp//web/" local="3805508749" remote="3805593900" Dst="-1" /><file name="2k3-06-006m.html" server="ftp.lolipop.jp//web/" local="3805508730" remote="3805593900" Dst="-1" /><file name="2k3-01-003m.html" server="ftp.lolipop.jp//web/" local="3805508706" remote="3805593900" Dst="-1" /><file name="2k3-06-001s.html" server="ftp.lolipop.jp//web/" local="3805508727" remote="3805593900" Dst="-1" /><file name="2k3-09-003n.html" server="ftp.lolipop.jp//web/" local="3805508740" remote="3805593900" Dst="-1" /><file name="2k3-12-004t.html" server="ftp.lolipop.jp//web/" local="3805508757" remote="3805593900" Dst="-1" /><file name="2k3-05-002n.html" server="ftp.lolipop.jp//web/" local="3805508722" remote="3805593900" Dst="-1" /><file name="2k3-04-003t.html" server="ftp.lolipop.jp//web/" local="3805508719" remote="3805593900" Dst="-1" /><file name="2k3-04-001m.html" server="ftp.lolipop.jp//web/" local="3805508716" remote="3805593900" Dst="-1" /><file name="2k3-03-003s.html" server="ftp.lolipop.jp//web/" local="3805508716" remote="3805593900" Dst="-1" /><file name="2k3-12-008t.html" server="ftp.lolipop.jp//web/" local="3805508760" remote="3805593900" Dst="-1" /><file name="2k3-08-002t.html" server="ftp.lolipop.jp//web/" local="3805508736" remote="3805593900" Dst="-1" /><file name="2k3-10-001m.html" server="ftp.lolipop.jp//web/" local="3805508742" remote="3805593900" Dst="-1" /><file name="2k3-10-003t.html" server="ftp.lolipop.jp//web/" local="3805508744" remote="3805593900" Dst="-1" /><file name="2k3-11-002m.html" server="ftp.lolipop.jp//web/" local="3805508749" remote="3805593900" Dst="-1" /><file name="2k3-11-005s.html" server="ftp.lolipop.jp//web/" local="3805508752" remote="3805593900" Dst="-1" /><file name="2k3-01-003n.html" server="ftp.lolipop.jp//web/" local="3805508706" remote="3805593900" Dst="-1" /><file name="2k3-09-003m.html" server="ftp.lolipop.jp//web/" local="3805508739" remote="3805593900" Dst="-1" /><file name="2k3-09-001t.html" server="ftp.lolipop.jp//web/" local="3805508738" remote="3805593900" Dst="-1" /><file name="2k3-05-005s.html" server="ftp.lolipop.jp//web/" local="3805508726" remote="3805593900" Dst="-1" /><file name="2k3-12-006n.html" server="ftp.lolipop.jp//web/" local="3805508758" remote="3805593900" Dst="-1" /><file name="2k3-09-004s.html" server="ftp.lolipop.jp//web/" local="3805508741" remote="3805593900" Dst="-1" /><file name="2k3-05-002m.html" server="ftp.lolipop.jp//web/" local="3805508722" remote="3805593900" Dst="-1" /><file name="2k3-09-001m.html" server="ftp.lolipop.jp//web/" local="3805508737" remote="3805593900" Dst="-1" /><file name="2k3-09-003t.html" server="ftp.lolipop.jp//web/" local="3805508740" remote="3805593900" Dst="-1" /><file name="2k3-05-002t.html" server="ftp.lolipop.jp//web/" local="3805508723" remote="3805593900" Dst="-1" /><file name="2k3-12-004n.html" server="ftp.lolipop.jp//web/" local="3805508757" remote="3805593900" Dst="-1" /><file name="2k3-01-001n.html" server="ftp.lolipop.jp//web/" local="3805508705" remote="3805593900" Dst="-1" /><file name="2k3-10-003m.html" server="ftp.lolipop.jp//web/" local="3805508743" remote="3805593900" Dst="-1" /><file name="2k3-03-001s.html" server="ftp.lolipop.jp//web/" local="3805508713" remote="3805593900" Dst="-1" /><file name="2k3-04-001t.html" server="ftp.lolipop.jp//web/" local="3805508717" remote="3805593900" Dst="-1" /><file name="2k3-04-003m.html" server="ftp.lolipop.jp//web/" local="3805508718" remote="3805593900" Dst="-1" /><file name="2k3-08-002m.html" server="ftp.lolipop.jp//web/" local="3805508735" remote="3805593900" Dst="-1" /><file name="2k3-12-008m.html" server="ftp.lolipop.jp//web/" local="3805508759" remote="3805593900" Dst="-1" /><file name="2k3-07-003n.html" server="ftp.lolipop.jp//web/" local="3805508733" remote="3805593900" Dst="-1" /><file name="2k3-10-005t.html" server="ftp.lolipop.jp//web/" local="3805508746" remote="3805593900" Dst="-1" /><file name="2k3-03-002m.html" server="ftp.lolipop.jp//web/" local="3805508714" remote="3805593900" Dst="-1" /><file name="2k3-04-007m.html" server="ftp.lolipop.jp//web/" local="3805508720" remote="3805593900" Dst="-1" /><file name="2k3-09-002s.html" server="ftp.lolipop.jp//web/" local="3805508739" remote="3805593900" Dst="-1" /><file name="2k3-05-004m.html" server="ftp.lolipop.jp//web/" local="3805508725" remote="3805593900" Dst="-1" /><file name="2k3-02-003t.html" server="ftp.lolipop.jp//web/" local="3805508713" remote="3805593900" Dst="-1" /><file name="2k3-05-003s.html" server="ftp.lolipop.jp//web/" local="3805508724" remote="3805593900" Dst="-1" /><file name="2k3-01-005n.html" server="ftp.lolipop.jp//web/" local="3805508709" remote="3805593900" Dst="-1" /><file name="2k3-11-003s.html" server="ftp.lolipop.jp//web/" local="3805508750" remote="3805593900" Dst="-1" /><file name="2k3-11-004m.html" server="ftp.lolipop.jp//web/" local="3805508751" remote="3805593900" Dst="-1" /><file name="2k3-11-006t.html" server="ftp.lolipop.jp//web/" local="3805508754" remote="3805593900" Dst="-1" /><file name="2k3-10-009n.html" server="ftp.lolipop.jp//web/" local="3805508748" remote="3805593900" Dst="-1" /><file name="2k3-01-007n.html" server="ftp.lolipop.jp//web/" local="3805508711" remote="3805593900" Dst="-1" /><file name="2k3-06-002n.html" server="ftp.lolipop.jp//web/" local="3805508729" remote="3805593900" Dst="-1" /><file name="2k3-11-006m.html" server="ftp.lolipop.jp//web/" local="3805508753" remote="3805593900" Dst="-1" /><file name="2k3-05-004t.html" server="ftp.lolipop.jp//web/" local="3805508725" remote="3805593900" Dst="-1" /><file name="2k3-05-001s.html" server="ftp.lolipop.jp//web/" local="3805508722" remote="3805593900" Dst="-1" /><file name="2k3-02-003m.html" server="ftp.lolipop.jp//web/" local="3805508712" remote="3805593900" Dst="-1" /><file name="2k3-03-002t.html" server="ftp.lolipop.jp//web/" local="3805508714" remote="3805593900" Dst="-1" /><file name="2k3-04-002s.html" server="ftp.lolipop.jp//web/" local="3805508718" remote="3805593900" Dst="-1" /><file name="2k3-04-007t.html" server="ftp.lolipop.jp//web/" local="3805508721" remote="3805593900" Dst="-1" /><file name="2k3-04-005m.html" server="ftp.lolipop.jp//web/" local="3805508720" remote="3805593900" Dst="-1" /><file name="2k3-10-005m.html" server="ftp.lolipop.jp//web/" local="3805508745" remote="3805593900" Dst="-1" /><file name="2k3-10-007t.html" server="ftp.lolipop.jp//web/" local="3805508747" remote="3805593900" Dst="-1" /><file name="2k3-07-001n.html" server="ftp.lolipop.jp//web/" local="3805508731" remote="3805593900" Dst="-1" /><file name="2k3-10-002s.html" server="ftp.lolipop.jp//web/" local="3805508742" remote="3805593900" Dst="-1" /><file name="2k3-11-006s.html" server="ftp.lolipop.jp//web/" local="3805508754" remote="3805593900" Dst="-1" /><file name="2k3-11-001m.html" server="ftp.lolipop.jp//web/" local="3805508749" remote="3805593900" Dst="-1" /><file name="2k3-11-003t.html" server="ftp.lolipop.jp//web/" local="3805508750" remote="3805593900" Dst="-1" /><file name="2k3-05-003t.html" server="ftp.lolipop.jp//web/" local="3805508724" remote="3805593900" Dst="-1" /><file name="2k3-05-001m.html" server="ftp.lolipop.jp//web/" local="3805508721" remote="3805593900" Dst="-1" /><file name="2k3-12-005n.html" server="ftp.lolipop.jp//web/" local="3805508758" remote="3805593900" Dst="-1" /><file name="2k3-05-00m.html" server="ftp.lolipop.jp//web/" local="3805508727" remote="3805593900" Dst="-1" /><file name="2k3-09-002t.html" server="ftp.lolipop.jp//web/" local="3805508739" remote="3805593900" Dst="-1" /><file name="2k3-08-003m.html" server="ftp.lolipop.jp//web/" local="3805508737" remote="3805593900" Dst="-1" /><file name="2k3-08-001t.html" server="ftp.lolipop.jp//web/" local="3805508735" remote="3805593900" Dst="-1" /><file name="2k3-12-009m.html" server="ftp.lolipop.jp//web/" local="3805508760" remote="3805593900" Dst="-1" /><file name="2k3-04-002m.html" server="ftp.lolipop.jp//web/" local="3805508717" remote="3805593900" Dst="-1" /><file name="2k3-07-004n.html" server="ftp.lolipop.jp//web/" local="3805508734" remote="3805593900" Dst="-1" /><file name="2k3-10-002t.html" server="ftp.lolipop.jp//web/" local="3805508743" remote="3805593900" Dst="-1" /><file name="2k3-08-001m.html" server="ftp.lolipop.jp//web/" local="3805508734" remote="3805593900" Dst="-1" /><file name="2k3-04-002t.html" server="ftp.lolipop.jp//web/" local="3805508718" remote="3805593900" Dst="-1" /><file name="2k3-03-002s.html" server="ftp.lolipop.jp//web/" local="3805508714" remote="3805593900" Dst="-1" /><file name="2k3-12-007n.html" server="ftp.lolipop.jp//web/" local="3805508759" remote="3805593900" Dst="-1" /><file name="2k3-09-005s.html" server="ftp.lolipop.jp//web/" local="3805508742" remote="3805593900" Dst="-1" /><file name="2k3-05-001t.html" server="ftp.lolipop.jp//web/" local="3805508722" remote="3805593900" Dst="-1" /><file name="2k3-05-003m.html" server="ftp.lolipop.jp//web/" local="3805508724" remote="3805593900" Dst="-1" /><file name="2k3-05-004s.html" server="ftp.lolipop.jp//web/" local="3805508725" remote="3805593900" Dst="-1" /><file name="2k3-11-004s.html" server="ftp.lolipop.jp//web/" local="3805508752" remote="3805593900" Dst="-1" /><file name="2k3-01-002n.html" server="ftp.lolipop.jp//web/" local="3805508705" remote="3805593900" Dst="-1" /><file name="2k3-11-003m.html" server="ftp.lolipop.jp//web/" local="3805508750" remote="3805593900" Dst="-1" /><file name="2k3-02-002m.html" server="ftp.lolipop.jp//web/" local="3805508712" remote="3805593900" Dst="-1" /><file name="2k3-09-004t.html" server="ftp.lolipop.jp//web/" local="3805508741" remote="3805593900" Dst="-1" /><file name="2k3-05-005t.html" server="ftp.lolipop.jp//web/" local="3805508726" remote="3805593900" Dst="-1" /><file name="2k3-12-003n.html" server="ftp.lolipop.jp//web/" local="3805508756" remote="3805593900" Dst="-1" /><file name="2k3-09-001s.html" server="ftp.lolipop.jp//web/" local="3805508737" remote="3805593900" Dst="-1" /><file name="2k3-06-003n.html" server="ftp.lolipop.jp//web/" local="3805508729" remote="3805593900" Dst="-1" /><file name="2k3-11-007m.html" server="ftp.lolipop.jp//web/" local="3805508754" remote="3805593900" Dst="-1" /><file name="2k3-11-005t.html" server="ftp.lolipop.jp//web/" local="3805508753" remote="3805593900" Dst="-1" /><file name="2k3-10-008n.html" server="ftp.lolipop.jp//web/" local="3805508748" remote="3805593900" Dst="-1" /><file name="2k3-01-006n.html" server="ftp.lolipop.jp//web/" local="3805508710" remote="3805593900" Dst="-1" /><file name="2k3-10-003s.html" server="ftp.lolipop.jp//web/" local="3805508744" remote="3805593900" Dst="-1" /><file name="2k3-10-004m.html" server="ftp.lolipop.jp//web/" local="3805508745" remote="3805593900" Dst="-1" /><file name="2k3-10-006t.html" server="ftp.lolipop.jp//web/" local="3805508747" remote="3805593900" Dst="-1" /><file name="2k3-04-006t.html" server="ftp.lolipop.jp//web/" local="3805508720" remote="3805593900" Dst="-1" /><file name="2k3-04-004m.html" server="ftp.lolipop.jp//web/" local="3805508719" remote="3805593900" Dst="-1" /><file name="2k3-03-003t.html" server="ftp.lolipop.jp//web/" local="3805508716" remote="3805593900" Dst="-1" /><file name="2k3-03-08-001m.html" server="ftp.lolipop.jp//web/" local="3805508716" remote="3805593900" Dst="-1" /><file name="2k3-04-003s.html" server="ftp.lolipop.jp//web/" local="3805508719" remote="3805593900" Dst="-1" /><file name="2k3-04-004t.html" server="ftp.lolipop.jp//web/" local="3805508720" remote="3805593900" Dst="-1" /><file name="2k3-03-003m.html" server="ftp.lolipop.jp//web/" local="3805508715" remote="3805593900" Dst="-1" /><file name="2k3-07-002n.html" server="ftp.lolipop.jp//web/" local="3805508732" remote="3805593900" Dst="-1" /><file name="2k3-10-006m.html" server="ftp.lolipop.jp//web/" local="3805508746" remote="3805593900" Dst="-1" /><file name="2k3-11-005m.html" server="ftp.lolipop.jp//web/" local="3805508752" remote="3805593900" Dst="-1" /><file name="2k3-06-001n.html" server="ftp.lolipop.jp//web/" local="3805508727" remote="3805593900" Dst="-1" /><file name="2k3-01-004n.html" server="ftp.lolipop.jp//web/" local="3805508707" remote="3805593900" Dst="-1" /><file name="2k3-11-002s.html" server="ftp.lolipop.jp//web/" local="3805508750" remote="3805593900" Dst="-1" /><file name="2k3-09-004m.html" server="ftp.lolipop.jp//web/" local="3805508740" remote="3805593900" Dst="-1" /><file name="2k3-02-002t.html" server="ftp.lolipop.jp//web/" local="3805508712" remote="3805593900" Dst="-1" /><file name="2k3-05-002s.html" server="ftp.lolipop.jp//web/" local="3805508723" remote="3805593900" Dst="-1" /><file name="2k3-09-003s.html" server="ftp.lolipop.jp//web/" local="3805508740" remote="3805593900" Dst="-1" /><file name="2k3-12-001n.html" server="ftp.lolipop.jp//web/" local="3805508755" remote="3805593900" Dst="-1" /><file name="2k3-05-005m.html" server="ftp.lolipop.jp//web/" local="3805508726" remote="3805593900" Dst="-1" /></dwsync>