<?xml version="1.0" encoding="utf-8" ?><dwsync><file name="Progress-table.103html" server="ftp-cokes.heteml.net//web/" local="3805508402" remote="3667647600" Dst="-1" /><file name="Progress-table.104html" server="ftp-cokes.heteml.net//web/" local="3805508402" remote="3667647600" Dst="-1" /><file name="Progress-table.105html" server="ftp-cokes.heteml.net//web/" local="3805508403" remote="3667647600" Dst="-1" /><file name="Progress-table.106html" server="ftp-cokes.heteml.net//web/" local="3805508403" remote="3667647600" Dst="-1" /><file name="Progress-table.html" server="ftp-cokes.heteml.net//web/" local="3805508403" remote="3667647600" Dst="-1" /><file name="Progress-table101.html" server="ftp-cokes.heteml.net//web/" local="3805508403" remote="3667647600" Dst="-1" /><file name="Progress-table102.html" server="ftp-cokes.heteml.net//web/" local="3805508403" remote="3667647600" Dst="-1" /><file name="Progress-table102.html" server="ftp.lolipop.jp//web/" local="3805508403" remote="3805596300" Dst="-1" /><file name="Progress-table.105html" server="ftp.lolipop.jp//web/" local="3805508403" remote="3805596300" Dst="-1" /><file name="Progress-table.104html" server="ftp.lolipop.jp//web/" local="3805508402" remote="3805596300" Dst="-1" /><file name="Progress-table.html" server="ftp.lolipop.jp//web/" local="3805508403" remote="3805596300" Dst="-1" /><file name="Progress-table101.html" server="ftp.lolipop.jp//web/" local="3805508403" remote="3805596300" Dst="-1" /><file name="Progress-table.106html" server="ftp.lolipop.jp//web/" local="3805508403" remote="3805596300" Dst="-1" /><file name="Progress-table.103html" server="ftp.lolipop.jp//web/" local="3805508402" remote="3805596300" Dst="-1" /></dwsync>